[
{"title": "Monthly_Top_First Subject", "type": "Pie", "data": [{"first_theme_name": "Computer Vision and Pattern Recognition (cs.CV)", "frequency": 649}, {"first_theme_name": "Machine Learning (cs.LG)", "frequency": 418}, {"first_theme_name": "Computation and Language (cs.CL)", "frequency": 370}, {"first_theme_name": "Machine Learning (stat.ML)", "frequency": 265}, {"first_theme_name": "Information Theory (cs.IT)", "frequency": 245}, {"first_theme_name": "Cryptography and Security (cs.CR)", "frequency": 140}, {"first_theme_name": "Distributed, Parallel, and Cluster Computing (cs.DC)", "frequency": 134}, {"first_theme_name": "Artificial Intelligence (cs.AI)", "frequency": 126}, {"first_theme_name": "Data Structures and Algorithms (cs.DS)", "frequency": 112}, {"first_theme_name": "Networking and Internet Architecture (cs.NI)", "frequency": 100}]},
{"title": "Monthly_Top_Second Subject", "type": "HorizBar1D", "config": {"index": "second_theme_name", "key": "frequency", "color": "blue"}, "data": [{"second_theme_name": "Machine Learning (stat.ML)", "frequency": 562}, {"second_theme_name": "Machine Learning (cs.LG)", "frequency": 537}, {"second_theme_name": "Artificial Intelligence (cs.AI)", "frequency": 307}, {"second_theme_name": "Computer Vision and Pattern Recognition (cs.CV)", "frequency": 119}, {"second_theme_name": "Neural and Evolutionary Computing (cs.NE)", "frequency": 81}, {"second_theme_name": "Distributed", "frequency": 70}, {"second_theme_name": " Parallel", "frequency": 70}, {"second_theme_name": " and Cluster Computing (cs.DC)", "frequency": 70}, {"second_theme_name": "Information Theory (cs.IT)", "frequency": 70}, {"second_theme_name": "Computation and Language (cs.CL)", "frequency": 69}]},
{"title": "Monthly_Top_Relation", "type": "VertBar2D", "config": {"index": "primary_subject", "key": ["Distributed", "Machine Learning (stat.ML)", "Dynamical Systems (math.DS)", "Machine Learning (cs.LG)", "Systems and Control (eess.SY)"], "axis": "frequency"}, "data": [{"primary_subject": "Machine Learning (cs.LG)", "Systems and Control (eess.SY)": 10, "Machine Learning (stat.ML)": 9, "Machine Learning (cs.LG)": 9, "Dynamical Systems (math.DS)": 4, "Distributed": 4}, {"primary_subject": "Machine Learning (stat.ML)", "Systems and Control (eess.SY)": 10, "Machine Learning (stat.ML)": 9, "Machine Learning (cs.LG)": 9, "Dynamical Systems (math.DS)": 4, "Distributed": 4}, {"primary_subject": "Computer Vision and Pattern Recognition (cs.CV)", "Systems and Control (eess.SY)": 10, "Machine Learning (stat.ML)": 9, "Machine Learning (cs.LG)": 9, "Dynamical Systems (math.DS)": 4, "Distributed": 4}, {"primary_subject": "Information Theory (cs.IT)", "Systems and Control (eess.SY)": 10, "Machine Learning (stat.ML)": 9, "Machine Learning (cs.LG)": 9, "Dynamical Systems (math.DS)": 4, "Distributed": 4}, {"primary_subject": "Social and Information Networks (cs.SI)", "Systems and Control (eess.SY)": 10, "Machine Learning (stat.ML)": 9, "Machine Learning (cs.LG)": 9, "Dynamical Systems (math.DS)": 4, "Distributed": 4}, {"primary_subject": "Distributed, Parallel, and Cluster Computing (cs.DC)", "Systems and Control (eess.SY)": 10, "Machine Learning (stat.ML)": 9, "Machine Learning (cs.LG)": 9, "Dynamical Systems (math.DS)": 4, "Distributed": 4}, {"primary_subject": "Cryptography and Security (cs.CR)", "Systems and Control (eess.SY)": 10, "Machine Learning (stat.ML)": 9, "Machine Learning (cs.LG)": 9, "Dynamical Systems (math.DS)": 4, "Distributed": 4}, {"primary_subject": "Computation and Language (cs.CL)", "Systems and Control (eess.SY)": 10, "Machine Learning (stat.ML)": 9, "Machine Learning (cs.LG)": 9, "Dynamical Systems (math.DS)": 4, "Distributed": 4}, {"primary_subject": "Data Structures and Algorithms (cs.DS)", "Systems and Control (eess.SY)": 10, "Machine Learning (stat.ML)": 9, "Machine Learning (cs.LG)": 9, "Dynamical Systems (math.DS)": 4, "Distributed": 4}, {"primary_subject": "Optimization and Control (math.OC)", "Systems and Control (eess.SY)": 10, "Machine Learning (stat.ML)": 9, "Machine Learning (cs.LG)": 9, "Dynamical Systems (math.DS)": 4, "Distributed": 4}]},
{"title": "Monthly_Top_Author", "type": "HorizBar1D", "config": {"index": "author_name", "key": "frequency", "color": "blue"}, "data": {"Onur Mutlu": 17, "Jiawei Zhang": 11, "Yang Liu": 10, "Saugata Ghose": 10, "Thomas Vogel": 9, "Holger Giese": 9, "Olga Krestinskaya": 9, "Donghyuk Lee": 9, "Maarten de Rijke": 8, "Fei Liu": 8}},
{"title": "Monthly_Top_Keyword", "type": "HorizBar1D", "config": {"index": "keyword", "key": "frequency", "color": "blue"}, "data": [{"keyword": "neural networks", "frequency": 164}, {"keyword": "learning", "frequency": 140}, {"keyword": "networks", "frequency": 113}, {"keyword": "reinforcement learning", "frequency": 92}, {"keyword": "neural network", "frequency": 73}, {"keyword": "deep learning", "frequency": 62}, {"keyword": "machine translation", "frequency": 55}, {"keyword": "convolutional neural", "frequency": 50}, {"keyword": "neural machine translation", "frequency": 47}, {"keyword": "convolutional neural networks", "frequency": 47}]}
]
